kiarina/lib/slack/__init__.py
kiarina/lib/slack/_settings.py
kiarina/lib/slack/py.typed
kiarina_lib_slack-1.35.0.dist-info/METADATA
kiarina_lib_slack-1.35.0.dist-info/WHEEL
kiarina_lib_slack-1.35.0.dist-info/RECORD
