Metadata-Version: 2.4
Name: kiarina-lib-slack
Version: 1.35.0
Summary: Slack API client library for kiarina namespace
Project-URL: Homepage, https://github.com/kiarina/kiarina-python
Project-URL: Repository, https://github.com/kiarina/kiarina-python
Project-URL: Issues, https://github.com/kiarina/kiarina-python/issues
Project-URL: Changelog, https://github.com/kiarina/kiarina-python/blob/main/packages/kiarina-lib-slack/CHANGELOG.md
Project-URL: Documentation, https://github.com/kiarina/kiarina-python/tree/main/packages/kiarina-lib-slack#readme
Author-email: kiarina <kiarinadawa@gmail.com>
Maintainer-email: kiarina <kiarinadawa@gmail.com>
License-Expression: MIT
Keywords: api,bot,client,pydantic,settings,slack
Classifier: Development Status :: 4 - Beta
Classifier: Intended Audience :: Developers
Classifier: Operating System :: OS Independent
Classifier: Programming Language :: Python :: 3
Classifier: Programming Language :: Python :: 3.12
Classifier: Programming Language :: Python :: 3.13
Classifier: Topic :: Software Development :: Libraries :: Python Modules
Classifier: Typing :: Typed
Requires-Python: >=3.12
Requires-Dist: pydantic-settings-manager>=2.3.0
Requires-Dist: pydantic-settings>=2.10.1
